README.md
setup.py
ping_emulator/__init__.py
ping_emulator/emulated_ping360.py
ping_emulator/emulated_ping_device.py
ping_emulator.egg-info/PKG-INFO
ping_emulator.egg-info/SOURCES.txt
ping_emulator.egg-info/dependency_links.txt
ping_emulator.egg-info/requires.txt
ping_emulator.egg-info/top_level.txt