Metadata-Version: 2.1
Name: ping-emulator
Version: 1.0.0
Summary: Python library to emulate Ping devices
Home-page: https://github.com/AlexisFetet/Ping360_emulator
Author: Alexis Fetet
Author-email: alexis.fetet@outlook.com
License: UNKNOWN
Platform: UNKNOWN
Classifier: Programming Language :: Python
Classifier: License :: OSI Approved :: MIT License
Classifier: Operating System :: OS Independent
Requires-Python: >=3.4
